.jshintrc
README.rst
README.txt
setup.py
docs/HISTORY.txt
docs/INSTALL.txt
docs/LICENSE.GPL
docs/LICENSE.txt
wildcard/__init__.py
wildcard.tinymceplugins.youtube.egg-info/PKG-INFO
wildcard.tinymceplugins.youtube.egg-info/SOURCES.txt
wildcard.tinymceplugins.youtube.egg-info/dependency_links.txt
wildcard.tinymceplugins.youtube.egg-info/entry_points.txt
wildcard.tinymceplugins.youtube.egg-info/namespace_packages.txt
wildcard.tinymceplugins.youtube.egg-info/not-zip-safe
wildcard.tinymceplugins.youtube.egg-info/requires.txt
wildcard.tinymceplugins.youtube.egg-info/top_level.txt
wildcard/tinymceplugins/__init__.py
wildcard/tinymceplugins/youtube/__init__.py
wildcard/tinymceplugins/youtube/add-youtube.pt
wildcard/tinymceplugins/youtube/configure.zcml
wildcard/tinymceplugins/youtube/tests.py
wildcard/tinymceplugins/youtube/profiles/default/metadata.xml
wildcard/tinymceplugins/youtube/profiles/default/tinymce.xml
wildcard/tinymceplugins/youtube/resources/tmceyoutube.js
wildcard/tinymceplugins/youtube/resources/youtube.png