Metadata-Version: 1.1
Name: wildcard.tinymceplugins.youtube
Version: 1.0
Summary: UNKNOWN
Home-page: https://github.com/collective/wildcard.tinymceplugins.youtube
Author: Nathan Van Gheem
Author-email: nathan@vangheem.us
License: GPL
Keywords: tinymce youtube plone
Platform: UNKNOWN
Classifier: Framework :: Plone
Classifier: Programming Language :: Python
Classifier: Framework :: Plone :: 4.3
